{
 "timestamp": 1754963008,
 "metal": "XAU",
 "currency": "USD",
 "exchange": "FOREXCOM",
 "symbol": "FOREXCOM:XAUUSD",
 "prev_close_price": 3342.42,
 "open_price": 3342.545,
 "low_price": 3342.545,
 "high_price": 3357.52,
 "open_time": 1754956800,
 "price": 3350.47,
 "ch": 8.05,
 "chp": 0.22,
 "ask": 3351.1,
 "bid": 3349.86,
 "price_gram_24k": 107.7201,
 "price_gram_22k": 98.7434,
 "price_gram_21k": 94.2551,
 "price_gram_20k": 89.7668,
 "price_gram_18k": 80.7901,
 "price_gram_16k": 71.8134,
 "price_gram_14k": 62.8367,
 "price_gram_10k": 44.8834
}